{
  "directions": {
    "above": [
      0.0,
      0.0,
      1.0
    ],
    "left": [
      -0.6563112735748291,
      -0.7544902563095093,
      0.0
    ],
    "right": [
      0.6563112735748291,
      0.7544902563095093,
      -0.0
    ],
    "below": [
      -0.0,
      -0.0,
      -1.0
    ],
    "front": [
      0.754490315914154,
      -0.6563112735748291,
      -0.0
    ],
    "behind": [
      -0.754490315914154,
      0.6563112735748291,
      0.0
    ]
  },
  "relationships": {
    "left": [
      [
        1,
        3
      ],
      [
        3
      ],
      [
        0,
        1,
        3
      ],
      []
    ],
    "right": [
      [
        2
      ],
      [
        0,
        2
      ],
      [],
      [
        0,
        1,
        2
      ]
    ],
    "front": [
      [
        1,
        2
      ],
      [],
      [
        1
      ],
      [
        0,
        1,
        2
      ]
    ],
    "behind": [
      [
        3
      ],
      [
        0,
        2,
        3
      ],
      [
        0,
        3
      ],
      []
    ]
  },
  "split": "new",
  "objects": [
    {
      "pixel_coords": [
        268,
        165,
        9.218392372131348
      ],
      "3d_coords": [
        1.384652853012085,
        -0.5918853878974915,
        0.699999988079071
      ],
      "size": "large",
      "color": "blue",
      "material": "rubber",
      "shape": "sphere",
      "rotation": 297.0367804281136
    },
    {
      "pixel_coords": [
        189,
        235,
        7.450680255889893
      ],
      "3d_coords": [
        2.0642528533935547,
        -2.8502705097198486,
        0.699999988079071
      ],
      "size": "large",
      "color": "blue",
      "material": "rubber",
      "shape": "cube",
      "rotation": 202.07640804861444
    },
    {
      "pixel_coords": [
        368,
        181,
        8.735533714294434
      ],
      "3d_coords": [
        2.891150712966919,
        0.24348184466362,
        0.699999988079071
      ],
      "size": "large",
      "color": "green",
      "material": "rubber",
      "shape": "sphere",
      "rotation": 9.697474755104608
    },
    {
      "pixel_coords": [
        164,
        98,
        11.870429039001465
      ],
      "3d_coords": [
        -2.341369867324829,
        -0.17937538027763367,
        0.699999988079071
      ],
      "size": "large",
      "color": "red",
      "material": "rubber",
      "shape": "cylinder",
      "rotation": 261.99601555488744
    }
  ],
  "image_index": 32,
  "image_filename": "CLEVR_new_000032.png"
}